{
  "_class": "bitmap",
  "booleanOperation": -1,
  "clippingMask": "{{0, 0}, {1, 1}}",
  "clippingMaskMode": 0,
  "do_objectID": "114A6EE5-C2C7-460B-B6A3-E3B79E96FA8C",
  "exportOptions": {
    "_class": "exportOptions",
    "do_objectID": "67411355-5D4B-4D6D-83D8-7351DF1D6155",
    "exportFormats": [
    ],
    "includedLayerIds": [
    ],
    "layerOptions": 0,
    "shouldTrim": false
  },
  "fillReplacesImage": false,
  "frame": {
    "_class": "rect",
    "constrainProportions": true,
    "do_objectID": "F6919433-DA54-46FE-B8A5-3E475FDDC8DF",
    "height": 391.5335463258787,
    "width": 380.6070287539937,
    "x": -0.6070287539936102,
    "y": -11.53354632587859
  },
  "hasClippingMask": false,
  "image": {
    "_class": "MSJSONFileReference",
    "_ref": "images/72ab223f2451d366d43be2ee183850500f6d9e40.png",
    "_ref_class": "MSImageData"
  },
  "intendedDPI": 72,
  "isFixedToViewport": false,
  "isFlippedHorizontal": false,
  "isFlippedVertical": false,
  "isLocked": false,
  "isVisible": true,
  "layerListExpandedType": 0,
  "name": "art",
  "nameIsFixed": false,
  "resizingConstraint": 63,
  "resizingType": 0,
  "rotation": 0,
  "shouldBreakMaskChain": false,
  "style": {
    "_class": "style",
    "do_objectID": "6FE76EB8-B6AA-4542-ABB5-F7E83D53FA8A",
    "endMarkerType": 0,
    "miterLimit": 10,
    "startMarkerType": 0,
    "windingRule": 1
  }
}