{
  "_class": "symbolInstance",
  "booleanOperation": -1,
  "clippingMaskMode": 0,
  "do_objectID": "62F7AB0F-1791-4D4D-89BC-B7B9E05BBDBA",
  "exportOptions": {
    "_class": "exportOptions",
    "do_objectID": "531554D9-2F56-46FB-B136-E0BF44C360EB",
    "exportFormats": [
    ],
    "includedLayerIds": [
    ],
    "layerOptions": 0,
    "shouldTrim": false
  },
  "frame": {
    "_class": "rect",
    "constrainProportions": false,
    "do_objectID": "219FD753-7A3D-4087-8757-2CFFD8964B43",
    "height": 150,
    "width": 1440,
    "x": 0,
    "y": 864
  },
  "hasClippingMask": false,
  "horizontalSpacing": 0,
  "isFixedToViewport": false,
  "isFlippedHorizontal": false,
  "isFlippedVertical": false,
  "isLocked": false,
  "isVisible": true,
  "layerListExpandedType": 0,
  "name": "Picture Title",
  "nameIsFixed": false,
  "overrideValues": [
    {
      "_class": "overrideValue",
      "do_objectID": "41E3BC6D-950E-4E96-A9C3-D74908DA0CD9",
      "overrideName": "690C7F26-DD6F-4BB2-BF8E-B9FF6CD6CED9_stringValue",
      "value": "Minor"
    }
  ],
  "resizingConstraint": 63,
  "resizingType": 0,
  "rotation": 0,
  "scale": 1,
  "shouldBreakMaskChain": false,
  "style": {
    "_class": "style",
    "do_objectID": "043C619F-1689-4684-AF27-1ED6E7D54290",
    "endMarkerType": 0,
    "miterLimit": 10,
    "startMarkerType": 0,
    "windingRule": 1
  },
  "symbolID": "9BC1F914-EB58-446C-A13B-EBDF2B76A8B9",
  "verticalSpacing": 0
}