{
  "_class": "shapeGroup",
  "booleanOperation": -1,
  "clippingMaskMode": 0,
  "do_objectID": "2666B5F4-9012-4A70-A688-D45EE97CFB72",
  "exportOptions": {
    "_class": "exportOptions",
    "do_objectID": "98590C8E-A92A-4F74-A071-948C52858296",
    "exportFormats": [
    ],
    "includedLayerIds": [
    ],
    "layerOptions": 0,
    "shouldTrim": false
  },
  "frame": {
    "_class": "rect",
    "constrainProportions": false,
    "do_objectID": "139965FF-8D47-493E-8A54-03082B0251D0",
    "height": 7.968862294288312,
    "width": 5.461734234234193,
    "x": 10.17622850122847,
    "y": 2.682169460932947
  },
  "hasClickThrough": false,
  "hasClippingMask": false,
  "isFixedToViewport": false,
  "isFlippedHorizontal": false,
  "isFlippedVertical": false,
  "isLocked": false,
  "isVisible": true,
  "layerListExpandedType": 1,
  "layers": [
    {
      "class": "shapePath",
      "id": "E868E96A-DC2B-4EF3-A249-0F5244BC8251"
    },
    {
      "class": "shapePath",
      "id": "C8644F1F-6590-4086-9227-4F822A4FBA3F"
    }
  ],
  "name": "G",
  "nameIsFixed": false,
  "resizingConstraint": 63,
  "resizingType": 0,
  "rotation": 0,
  "shouldBreakMaskChain": false,
  "style": {
    "_class": "style",
    "do_objectID": "10C442F0-4C41-402F-A21C-4A440A909E5E",
    "endMarkerType": 0,
    "fills": [
      {
        "_class": "fill",
        "color": {
          "_class": "color",
          "alpha": 1,
          "blue": 0.9333333333333333,
          "green": 0.9333333333333333,
          "red": 0.9333333333333333
        },
        "fillType": 0,
        "isEnabled": true,
        "noiseIndex": 0,
        "noiseIntensity": 0,
        "patternFillType": 1,
        "patternTileScale": 1
      }
    ],
    "miterLimit": 10,
    "startMarkerType": 0,
    "windingRule": 0
  },
  "windingRule": 0
}