{
  "_class": "bitmap",
  "booleanOperation": -1,
  "clippingMask": "{{0, 0}, {1, 1}}",
  "clippingMaskMode": 0,
  "do_objectID": "EAD7A35E-D9CA-471D-AC7E-7E926C47BD82",
  "exportOptions": {
    "_class": "exportOptions",
    "do_objectID": "7775180C-47E9-49C8-8C2D-BB9B6B8C5A56",
    "exportFormats": [
    ],
    "includedLayerIds": [
    ],
    "layerOptions": 0,
    "shouldTrim": false
  },
  "fillReplacesImage": false,
  "frame": {
    "_class": "rect",
    "constrainProportions": true,
    "do_objectID": "4BAC21EE-23B7-4D0C-ABE9-CED47F158100",
    "height": 1024,
    "width": 1637,
    "x": 0,
    "y": 0
  },
  "hasClippingMask": false,
  "image": {
    "_class": "MSJSONFileReference",
    "_ref": "images/931cda601cb1a2471bcafa8bd283c840a9840f7d.png",
    "_ref_class": "MSImageData"
  },
  "intendedDPI": 72,
  "isFixedToViewport": false,
  "isFlippedHorizontal": false,
  "isFlippedVertical": false,
  "isLocked": false,
  "isVisible": true,
  "layerListExpandedType": 0,
  "name": "bg1",
  "nameIsFixed": false,
  "resizingConstraint": 63,
  "resizingType": 0,
  "rotation": 0,
  "shouldBreakMaskChain": false,
  "style": {
    "_class": "style",
    "do_objectID": "0F09EA93-6693-40EB-A1DC-0E068C507E3C",
    "endMarkerType": 0,
    "miterLimit": 10,
    "startMarkerType": 0,
    "windingRule": 1
  }
}