{
  "_class": "shapeGroup",
  "booleanOperation": -1,
  "clippingMaskMode": 0,
  "do_objectID": "5E1F6339-43C7-4B6A-BD70-661379FBA3DD",
  "exportOptions": {
    "_class": "exportOptions",
    "do_objectID": "6F3B8822-5B70-4724-A139-4043DCD1BD0F",
    "exportFormats": [
    ],
    "includedLayerIds": [
    ],
    "layerOptions": 0,
    "shouldTrim": false
  },
  "frame": {
    "_class": "rect",
    "constrainProportions": false,
    "do_objectID": "C348A015-DB5E-43E9-BE73-02E80D4E3059",
    "height": 5.654559363163382,
    "width": 4.257420051557661,
    "x": 8.406330972193274,
    "y": 1.269739867475723
  },
  "hasClickThrough": false,
  "hasClippingMask": false,
  "isFixedToViewport": false,
  "isFlippedHorizontal": false,
  "isFlippedVertical": false,
  "isLocked": false,
  "isVisible": true,
  "layerListExpandedType": 1,
  "layers": [
    {
      "class": "shapePath",
      "id": "837CAC5C-04C5-4CBB-AADC-809A0E537672"
    },
    {
      "class": "shapePath",
      "id": "19B5B520-EF0C-4970-AD6C-BF5B552DFEC4"
    }
  ],
  "name": "A",
  "nameIsFixed": false,
  "resizingConstraint": 63,
  "resizingType": 0,
  "rotation": 0,
  "shouldBreakMaskChain": false,
  "style": {
    "_class": "style",
    "do_objectID": "A42AAA78-BC38-4483-B226-2D31918028B6",
    "endMarkerType": 0,
    "fills": [
      {
        "_class": "fill",
        "color": {
          "_class": "color",
          "alpha": 1,
          "blue": 0.9333333333333333,
          "green": 0.9333333333333333,
          "red": 0.9333333333333333
        },
        "fillType": 0,
        "isEnabled": true,
        "noiseIndex": 0,
        "noiseIntensity": 0,
        "patternFillType": 1,
        "patternTileScale": 1
      }
    ],
    "miterLimit": 10,
    "startMarkerType": 0,
    "windingRule": 0
  },
  "windingRule": 0
}