{
  "_class": "group",
  "booleanOperation": -1,
  "clippingMaskMode": 0,
  "do_objectID": "EB7CB486-1478-4E06-9E7E-1A8C8BF9EC23",
  "exportOptions": {
    "_class": "exportOptions",
    "do_objectID": "A6510AC4-D1B9-4DFF-B143-76BEDCA1021C",
    "exportFormats": [
    ],
    "includedLayerIds": [
    ],
    "layerOptions": 0,
    "shouldTrim": false
  },
  "frame": {
    "_class": "rect",
    "constrainProportions": false,
    "do_objectID": "08F43D82-6E9A-4FE2-867A-55C638A9B2D0",
    "height": 11,
    "width": 95,
    "x": 104,
    "y": 54
  },
  "hasClickThrough": false,
  "hasClippingMask": false,
  "isFixedToViewport": false,
  "isFlippedHorizontal": false,
  "isFlippedVertical": false,
  "isLocked": false,
  "isVisible": true,
  "layerListExpandedType": 0,
  "layers": [
    {
      "class": "group",
      "id": "745112EC-E2D6-4ABC-BA7F-771807CFDDFF"
    },
    {
      "class": "group",
      "id": "72DDACD7-BCFC-41E2-8295-B53CA2467BA9"
    },
    {
      "class": "group",
      "id": "29CD1C97-624A-41E0-B32F-2FE5B045627B"
    }
  ],
  "name": "tag",
  "nameIsFixed": false,
  "resizingConstraint": 63,
  "resizingType": 0,
  "rotation": 0,
  "shouldBreakMaskChain": false,
  "style": {
    "_class": "style",
    "do_objectID": "93EA6F35-EC0C-49BB-9740-1177C2C152BC",
    "endMarkerType": 0,
    "fills": [
      {
        "_class": "fill",
        "color": {
          "_class": "color",
          "alpha": 1,
          "blue": 0,
          "green": 0,
          "red": 0
        },
        "fillType": 0,
        "isEnabled": true,
        "noiseIndex": 0,
        "noiseIntensity": 0,
        "patternFillType": 1,
        "patternTileScale": 1
      }
    ],
    "miterLimit": 10,
    "startMarkerType": 0,
    "windingRule": 1
  }
}