{
  "_class": "shapeGroup",
  "booleanOperation": -1,
  "clippingMaskMode": 0,
  "do_objectID": "06917D76-177A-4BD5-9CE7-F19AF357D859",
  "exportOptions": {
    "_class": "exportOptions",
    "do_objectID": "4A781CD8-6C8C-4ECA-BF08-88EF769B03CA",
    "exportFormats": [
    ],
    "includedLayerIds": [
    ],
    "layerOptions": 0,
    "shouldTrim": false
  },
  "frame": {
    "_class": "rect",
    "constrainProportions": false,
    "do_objectID": "E358FFB1-0FB5-4D64-99BE-F2502B3333A3",
    "height": 5.680974958495137,
    "width": 4.714845961248496,
    "x": 20.69166461916467,
    "y": 2.744999999999963
  },
  "hasClickThrough": false,
  "hasClippingMask": false,
  "isFixedToViewport": false,
  "isFlippedHorizontal": false,
  "isFlippedVertical": false,
  "isLocked": false,
  "isVisible": true,
  "layerListExpandedType": 1,
  "layers": [
    {
      "class": "shapePath",
      "id": "2198C2E8-084A-494D-8928-81754D5AB86C"
    },
    {
      "class": "shapePath",
      "id": "FC2BAC52-ED86-4CD6-A4EC-94FEFC42D15D"
    }
  ],
  "name": "E",
  "nameIsFixed": false,
  "resizingConstraint": 63,
  "resizingType": 0,
  "rotation": 0,
  "shouldBreakMaskChain": false,
  "style": {
    "_class": "style",
    "do_objectID": "7C7A32F5-2F53-40A3-9B16-D924BE982AF0",
    "endMarkerType": 0,
    "fills": [
      {
        "_class": "fill",
        "color": {
          "_class": "color",
          "alpha": 1,
          "blue": 0.9333333333333333,
          "green": 0.9333333333333333,
          "red": 0.9333333333333333
        },
        "fillType": 0,
        "isEnabled": true,
        "noiseIndex": 0,
        "noiseIntensity": 0,
        "patternFillType": 1,
        "patternTileScale": 1
      }
    ],
    "miterLimit": 10,
    "startMarkerType": 0,
    "windingRule": 0
  },
  "windingRule": 0
}